pplot/__init__.py
pplot/basic_source.py
pplot/compat2.py
pplot/compat3.py
pplot/constants.py
pplot/csv_source.py
pplot/figure.py
pplot/functions.py
pplot/panel.py
pplot/pkgdata.py
pplot/ptypes.py
pplot/series.py
pplot/__pycache__/pkgdata.cpython-35.pyc
pplot/__pycache__/pkgdata.cpython-36.pyc
pplot-1.1.4.dist-info/METADATA
pplot-1.1.4.dist-info/RECORD
pplot-1.1.4.dist-info/WHEEL
pplot-1.1.4.dist-info/top_level.txt
